LICENSE
MANIFEST.in
README.rst
setup.cfg
setup.py
versioneer.py
tests/__init__.py
tests/test_general.py
tpDcc/__init__.py
tpDcc/libs/__init__.py
tpDcc/libs/options/__init__.py
tpDcc/libs/options/__logging__.ini
tpDcc/libs/options/__version__.py
tpDcc/libs/options/_version.py
tpDcc/libs/options/core/__init__.py
tpDcc/libs/options/core/factory.py
tpDcc/libs/options/core/option.py
tpDcc/libs/options/core/optionlist.py
tpDcc/libs/options/core/viewer.py
tpDcc/libs/options/options/__init__.py
tpDcc/libs/options/options/bool.py
tpDcc/libs/options/options/color.py
tpDcc/libs/options/options/combo.py
tpDcc/libs/options/options/dictionary.py
tpDcc/libs/options/options/directory.py
tpDcc/libs/options/options/file.py
tpDcc/libs/options/options/float.py
tpDcc/libs/options/options/integer.py
tpDcc/libs/options/options/list.py
tpDcc/libs/options/options/script.py
tpDcc/libs/options/options/text.py
tpDcc/libs/options/options/title.py
tpDcc/libs/options/options/vector3.py
tpDcc_libs_options.egg-info/PKG-INFO
tpDcc_libs_options.egg-info/SOURCES.txt
tpDcc_libs_options.egg-info/dependency_links.txt
tpDcc_libs_options.egg-info/not-zip-safe
tpDcc_libs_options.egg-info/requires.txt
tpDcc_libs_options.egg-info/top_level.txt