Metadata-Version: 2.1
Name: tpDcc-libs-options
Version: 0.0.1
Summary: Library to easily create data driven options/attributes views.
Home-page: https://github.com/tpDcc/tpDcc-libs-options
Author: Tomas Poveda
Author-email: tpovedatd@gmail.com
License: MIT
Platform: UNKNOWN
Provides-Extra: dev
Provides-Extra: test
